{
    "name": "Mattso's Epic Swag Image Collection",
    "path": "emotes",
    "emotes" : [
        {
            "name": "fr",
            "type": ".png"
        },
        {
            "name": "clap",
            "type": ".gif"
        },
        {
            "name": "KanyeStare",
            "type": ".gif"
        },
        {
            "name": "peepoClap",
            "type": ".gif"
        },
        {
            "name": "peepoHappy",
            "type": ".png"
        },
        {
            "name": "blobDance",
            "type": ".gif"
        },
        {
            "name": "ricardoFlick",
            "type": ".gif"
        },
        {
            "name": "popcat",
            "type": ".gif"
        },
        {
            "name": "peepoLeave",
            "type": ".gif"
        },
        {
            "name": "catJAM",
            "type": ".gif"
        },
        {
            "name": "sonic",
            "type": ".gif"
        },
        {
            "name": "sonicDance",
            "type": ".gif"
        },
        {
            "name": "Jeff",
            "type": ".png"
        },
        {
            "name": "susDrip",
            "type": ".gif"
        },
        {
            "name": "susPls",
            "type": ".gif"
        },
        {
            "name": "rickDance",
            "type": ".gif"
        },
        {
            "name": "rickPls",
            "type": ".gif"
        },
        {
            "name": "funneJoji",
            "type": ".png"
        }
    ]
}
